LICENSE.md
MANIFEST.in
README.md
setup.cfg
setup.py
scripts/LONG_DESCRIPTION.txt
scripts/__init__.py
scripts/git.py
scripts/setup.py
scripts/utils.py
scripts/version.py.in
scripts/versioning.py
src/nauka/__init__.py
src/nauka/ap.py
src/nauka/fhs.py
src/nauka/version.py
src/nauka.egg-info/PKG-INFO
src/nauka.egg-info/SOURCES.txt
src/nauka.egg-info/dependency_links.txt
src/nauka.egg-info/not-zip-safe
src/nauka.egg-info/requires.txt
src/nauka.egg-info/top_level.txt
src/nauka/exp/__init__.py
src/nauka/exp/experiment.py
src/nauka/utils/__init__.py
src/nauka/utils/lr.py
src/nauka/utils/numpy/__init__.py
src/nauka/utils/numpy/random/__init__.py
src/nauka/utils/random/__init__.py
src/nauka/utils/torch/__init__.py
src/nauka/utils/torch/cuda/__init__.py
src/nauka/utils/torch/optim/__init__.py
src/nauka/utils/torch/random/__init__.py